Workbook

Sheet Resources
A1: Resource | B1: Acquired From | C1: Description | D1: Used For | E1: Refines Into
A2: Timber | B2: Collect from dead trees, Spirits assigned to Sawmill, Found in shards (Memory World) from fallen buildings or wooden wreckage. | C2: Your basic organic building resource. Salvaged planks, beams, and scrap wood gathered from the environment or produced by follower tasks. | D2: Early and mid-tier constructions, decorations, repairs. Refined later for higher tier constructions. | E2: Boards
A3: Rock | B3: Harvest from stones or gravestones around the base, Spirits assigned to Quarry, found in shards from collapsed ruins or altars. | C3: A basic sturdy building material gathered from old ruins and broken gravestones. Heavy and reliable; spirits collect it over time, or you can harvest large chunks while exploring. | D3: Core construction of foundation, paths, and sturdy structures. Repairs after ghosts damage buildings. Upgrades that require stronger material. | E3: Bricks
A4: Boards | B4: Crafted at Workshop (3–5 Timber per Board). | C4: Processed Timber: clean, cut, reinforced planks for higher quality construction. Crafted by spirits handling carpentry. | D4: Upgraded structures, decorations, repairs.
A5: Bricks | B5: Crafted at Workshop (3–5 Rock per Brick). | C5: Refined Rock: shaped and hardened building blocks for durable structures. Represents high-tier durability material. | D5: High-tier buildings and decorative structures.
A6: Token Shards | B6: Dungeons, Mines. | C6: Small cracked bits of old currency; worth little alone but can be reforged. | D6: Refined at the workshop to make full Tokens or Medallions. | E6: Tokens
A7: Tokens | B7: Dungeons, followers, sales. | C7: The standard currency. Heavy metal coins used by the dead to trade, repair, and pay for rituals. | D7: General purchases, structure upgrades, decorations, and rituals. | E7: Medallions
A8: Medallions | B8: Crafted from Token Shards (10 Shards = 1 Token, 10 Tokens = 1 Medallion). | C8: Refined, high-value currency. | D8: Major building upgrades, rare trades, and high-tier rituals.
A9: Remains | B9: Dungeon runs, banished ghosts, ritual aftermath. | C9: Fragments and ash left behind after spirits pass, are banished, or defeated. | D9: Fuel for rituals, potion catalyst, crafting material for ash-based items.
A10: Essence | B10: Generated passively by happy ghosts or found in dungeons. | C10: Emotional energy produced by content spirits doing tasks. Used for upgrades, repairs, and rituals. | D10: Upgrades, crafting, rituals, Grace conversion.
A11: Grace | B11: Earned by performing rituals or releasing ghosts peacefully. | C11: Currency for your upgrade tree — unlock new buildings, rituals, and systems. | D11: Upgrade tree progression, feature unlocks.
A12: Bond | B12: Increases through ghost interactions: gifting, conversation, fulfilling requests. | C12: Represents your personal connection to each ghost. Influences productivity and stability. | D12: Improves work efficiency and prevents unrest spread.
A13: Spirit | B13: Bound during rituals or rescued in dungeons. | C13: Each ghost you care for; they perform tasks, produce Essence, and have unique temperaments. | D13: Central to every system: Essence production, tasks, morale, and narrative arcs.
A14: Ectoplasm | B14: Produced during Manifest events or defeating Manifesting ghosts. | C14: The byproduct of Manifest events; gooey residue of leaking emotion. | D14: Fertilizer for Garden of Rest, potion ingredient, crafting reagent.
A15: Appetite | B15: Passive decay per day; restored by feeding Offerings or Ectofruit. | C15: How long ghosts remain stable before acting out. Low Appetite causes unrest and erratic behavior. | D15: Feeding and emotional stability management.
A16: Flicker | B16: From overworking ghosts or ignoring rest cycles. | C16: Represents emotional burnout; overworked ghosts flicker and slow tasks. | D16: Determines rest and recovery needs for ghosts.
A17: Unrest | B17: Triggered when multiple ghosts lose Contentment simultaneously. | C17: The revolt state — when multiple spirits begin acting out and vandalizing. | D17: Cleansing rituals, repairs, and mood recovery.
A18: Manifest | B18: Low Contentment or hunger; unstable spirits leak Essence. | C18: Death isn’t tidy — leaking ghosts leave ectoplasm that decays morale if ignored. | D18: Clean-up gameplay loop, Ectoplasm farming.
A19: Temperament System | B19: Predefined per ghost on spawn. | C19: Defines ghost behavior style (Mournful, Trickster, Spiteful, Cold, Fanatic, etc.). | D19: AI logic, task modification, emergent base chaos.
... A23: Memoria | B23: Peacefully released ghosts. | C23: Prestige resource representing remembrance and closure. | D23: Permanent upgrades, shrine construction, narrative progression.
A24: Relic Fragments | B24: Dropped by defeated Wraiths and Bosses. | C24: Fragments of emotion and memory used for crafting relics and charms. | D24: Crafted into Charms at the Relic Forge. | E24: Charms
A25: Charms | B25: Crafted at the Relic Forge using Relic Fragments. | C25: Small talismans imbued with ghostly memory; gifted to spirits. | D25: Modify Temperament effects, stabilize moods, grant small perks.
A26: Cloth | B26: Made from ghost threads or salvaged shrouds. | C26: Soft material with spectral shimmer, used for decoration and comfort items. | D26: Beds, banners, decorative items.
A27: Glass | B27: Salvaged from lanterns, jars, or ruins. | C27: Transparent and fragile; used for lighting, ritual implements. | D27: Lamps, ritual tools, decorative objects.
A28: Wax | B28: Harvested from melted candles and ritual drippings. | C28: Sticky, renewable resource for lighting and luxury items. | D28: Candle crafting, lighting fixtures, decor.

Sheet Buildings
A1: Building | B1: Description | C1: Unlock Timing
A2: Sawmill | B2: Produces Timber over time. | C2: Early-Game. Foundation for the economy.
A3: Quarry | B3: Produces Rock over time. | C3: Early-Game. Complements Sawmill.
A4: Workshop | B4: Converts raw materials into refined forms (Boards/Bricks). | C4: Mid-Game upgrade.
A5: Storage | B5: Stores excess materials safely. | C5: Mid-Game convenience structure.
A6: Relic Forge | B6: Forges Charms from Relic Fragments. | C6: Core-Game progression.
A7: Alchemy Table | B7: Brews Potions using Ectoplasm, Essence, and Remains. | C7: Mid to Late-Game system.

Sheet Emotional_Systems
A1: System | B1: Acquired / Triggered By | C1: Description | D1: Used For
A2: Contentment | B2: Raised by feeding, soothing, storytelling, and giving gifts. | C2: Represents emotional stability of spirits. Low Contentment leads to hauntings, sabotage, and rebellion. | D2: Feeds Essence generation, determines Memento rate, prevents Unrest.
A3: Essence | B3: Produced by Content ghosts or collected from dungeons. | C3: Emotional energy produced by content spirits doing tasks. | D3: Used for upgrades, repairs, rituals, and Grace generation.
A4: Grace | B4: Gained from rituals and releasing ghosts peacefully. | C4: Currency for upgrade tree — new buildings, rituals, and systems. | D4: Progression gating and upgrade economy.
A5: Bond | B5: Grows through conversation, gifting, rescuing ghosts in runs. | C5: Represents relationship strength with each ghost; small buffs for productivity and temperament control. | D5: Affects work reliability, request frequency, and event chains.
A6: Spirit | B6: Bound through Altar rituals or rescued from dungeons. | C6: Each ghost you care for; performs tasks, produces Essence, and has a unique temperament. | D6: Central to all systems: production, morale, dungeon runs.
A7: Ectoplasm | B7: Manifest events and enemy drops. | C7: Byproduct of emotional instability; sticky residue of leaking Essence. | D7: Used for Garden fertilizer, potions, rituals, and crafting.
A8: Appetite | B8: Passively decreases each day; restored by feeding Offerings/Ectofruit. | C8: Measures how long ghosts stay calm before unrest. | D8: Feeding ghosts, restoring stability, preventing Manifest.
A9: Flicker | B9: Overwork and emotional neglect. | C9: Represents burnout. Spirits slow tasks and lose mood faster. | D9: Encourages pacing, assigning rest or low-stress jobs.
A10: Unrest | B10: Triggered by low Contentment across multiple ghosts. | C10: Collective revolt event — vandalism, hauntings, chaos. | D10: Managed through rituals, soothing actions, and repairs.
A11: Manifest | B11: Low Contentment or neglect. | C11: Spirits physically leak Essence as ectoplasm, lowering morale if ignored. | D11: Cleaning loop, resource generation, visual storytelling.
A12: Temperament System | B12: Assigned on spawn; static per ghost. | C12: Defines behavior archetype (Mournful, Trickster, Spiteful, Cold, Fanatic, etc.). | D12: Drives AI quirks, conflicts, and base drama.
... A21: Charms | B21: Crafted from Relic Fragments at the Forge. | C21: Talismans given to ghosts to influence their stats. | D21: Permanent buffs and mood stabilizers.

Sheet Crafting_Chains
A1: Input | B1: Output | C1: Conversion / Ratio | D1: Created At | E1: Used For
A2: Timber | B2: Boards | C2: 3–5 Timber per Board | D2: Workshop | E2: Building upgrades, decor, and repairs
A3: Rock | B3: Bricks | C3: 3–5 Rock per Brick | D3: Workshop | E3: High-tier building construction
A4: Boards | B4: Structures | C4: Used as component | D4: Workshop/Construction | E4: Improved durability buildings
A5: Bricks | B5: Structures | C5: Used as component | D5: Workshop/Construction | E5: Permanent or luxury buildings
A6: Token Shards | B6: Tokens | C6: 10 Shards per Token | D6: Workshop | E6: Currency refinement
A7: Tokens | B7: Medallions | C7: 10 Tokens per Medallion | D7: Workshop | E7: High-value trades and rituals
A8: Essence | B8: Grace | C8: Spend Essence via Rituals | D8: Altar | E8: Upgrade tree unlocks
A9: Remains | B9: Ritual Fuel / Potions | C9: Consumed in crafting or rituals | D9: Altar / Alchemy Table | E9: Cleansing, potions, upgrades
A10: Ectoplasm | B10: Fertilizer / Potions | C10: Used as catalyst or fertilizer | D10: Garden / Alchemy | E10: Improved yields and potion stability
A11: Relic Fragments | B11: Charms | C11: 3–5 Fragments per Charm | D11: Relic Forge | E11: Follower buffs
A12: Flowers | B12: Offerings | C12: Harvested from Garden of Rest | D12: Garden | E12: Feeding and decorative usage
... A15: Memoria | B15: Permanent Bonuses | C15: Automatically stored | D15: Meta Progression | E15: Passive endgame boosts

Sheet Economy_Flowchart
A1: Resource Loop | B1: Flow Path | C1: Category | D1: Purpose / Design Notes
A2: Timber Loop | B2: Timber → Boards → Structures | C2: Material | D2: Core building loop: establishes foundational construction economy.
A3: Rock Loop | B3: Rock → Bricks → Structures | C3: Material | D3: Heavy, durable economy; pairs with Timber for balanced pacing.
A4: Essence Loop | B4: Essence → Grace → Upgrades | C4: Emotional | D4: Spiritual feedback loop; happiness creates progress.
A5: Remains Loop | B5: Remains → Potions / Rituals → Grace | C5: Crafting | D5: Death → renewal; loss fuels care and advancement.
A6: Mementos Loop | B6: Mementos → Dungeon Runs → Essence / Remains | C6: Emotional | D6: Harmony enables exploration, exploration reinforces harmony.
A7: Token Loop | B7: Token Shards → Tokens → Medallions → Upgrades / Rituals | C7: Currency | D7: Economic loop; converts exploration reward into high-tier value.
A8: Ectoplasm Loop | B8: Manifest → Ectoplasm → Fertilizer / Potions | C8: Crafting | D8: Chaos recycling: cleaning unrest yields growth potential.
A9: Relic Loop | B9: Relic Fragments → Charms → Ghost Buffs | C9: Crafting | D9: Dungeon mastery; victory becomes permanent emotional support.
A10: Garden Loop | B10: Flowers → Offerings → Feed Spirits → Contentment → Essence | C10: Emotional | D10: Daily care cycle; nurturing yields both joy and productivity.
A11: Bond Loop | B11: Requests → Bond → Productivity / Stability | C11: Emotional | D11: Relationship economy; emotional investment yields efficiency.
A12: Grace Loop | B12: Grace → Unlocks → Better Systems → More Contentment | C12: Emotional | D12: Meta progression; compassion strengthens sanctuary systems.

Sheet Legend
A1: Category | B1: Color Description
A2: Material | B2: Material Loop Color
A3: Crafting | B3: Crafting Loop Color
A4: Currency | B4: Currency Loop Color
A5: Emotional | B5: Emotional Loop Color
A8: Each 'Flow Path' visually represents resource refinement and emotional feedback chains.
A9: This sheet serves as the visual design map for production economy relationships.

Sheet Seeds
A1: SeedID | B1: Seed Name | C1: Produces PlantID | D1: Base Cost Tokens | E1: Base Cost Essence | F1: Required Remains | G1: Unlocked At (Upgrade/Quest) | H1: Preferred Temperaments | I1: Notes
A2: SEED_WHISPERBLOOM | B2: Whisperbloom Seed | C2: WHISPERBLOOM | D2: 1 | E2: 10 | F2: 0 | G2: Garden Tier 1 | H2: Mournful / Bright | I2: Starter seed; soothing baseline.
A3: SEED_GRIEFROOT | B3: Griefroot Thorn | C3: GRIEFROOT | D3: 2 | E3: 12 | F3: 0 | G3: Garden Tier 1 | H3: Stoic / Cold | I3: Grows faster near unhappy ghosts; low-risk rot.
A4: SEED_MIRTHPETAL | B4: Mirthpetal Bulb | C4: MIRTHPETAL | D4: 1 | E4: 8 | F4: 0 | G4: Garden Tier 1 | H4: Bright / Trickster | I4: Boosts Bond; synergizes with Charms of Mirth.
A5: SEED_FORGETMEBUD | B5: Forget‑Me‑Bud Pod | C5: FORGETMEBUD | D5: 2 | E5: 15 | F5: 0 | G5: Garden Tier 2 | H5: Mournful / Stoic | I5: Supports Grace gain over time.
A6: SEED_ASHBLOSSOM | B6: Ashblossom Ash | C6: ASHBLOSSOM | D6: 0 | E6: 0 | F6: 1 | G6: Garden Tier 2 | H6: Cold / Stoic | I6: Consumes Remains; yields Essence + Remains.
A7: SEED_KINDLEFERN | B7: Kindlefern Spore | C7: KINDLEFERN | D7: 1 | E7: 10 | F7: 0 | G7: Garden Tier 2 | H7: Fanatic / Bright | I7: Small Grace & Ectofruit synergy.
A8: SEED_LAMENT_LILY | B8: Lament Lily Rhizome | C8: LAMENT_LILY | D8: 1 | E8: 10 | F8: 0 | G8: Garden Tier 2 | H8: Mournful / — | I8: Sleep & Flicker recovery aura.
A9: SEED_WRAITHVINE | B9: Wraithvine Spine | C9: WRAITHVINE | D9: 0 | E9: 0 | F9: 3 | G9: Quest: Cursed Soil | H9: Cold / Stoic | I9: High risk/high reward potion base.
A10: SEED_PEACEBUD | B10: Peacebud Sigil | C10: PEACEBUD | D10: 0 | E10: 0 | F10: 0 | G10: Global Harmony Event | H10: All | I10: Not buyable; triggers at 90%+ Contentment.

Sheet Garden_Outputs
A1: OutputID | B1: Source PlantID | C1: Output Name | D1: Quantity | E1: Unit Type | F1: Use Case | G1: Consumed By | H1: Base Value (Tokens) | I1: Alt Use | J1: Notes
A2: OUT_WHISPERBLOOM_FLOWER | B2: WHISPERBLOOM | C2: Whisperbloom Flower | D2: 2 | E2: Item | F2: Offering (feed) | G2: Appetite System | H2: 2 | I2: Potion: Calm Tea | J2: Soothing ingredient; boosts Contentment on feed.
A3: OUT_GRIEFROOT_THORNS | B3: GRIEFROOT | C3: Griefroot Thorns | D3: 1 | E3: Bundle | F3: Potion: Thorn Tonic (defense buff) | G3: Potions | H3: 4 | I3: Charm: Restraint Core | J3: Small rot risk if over-fertilized.
A4: OUT_GRIEFROOT_RESIN | B4: GRIEFROOT | C4: Sorrow Resin | D4: 1 | E4: Item | F4: Charm crafting binder | G4: Charms | H4: 5 | I4: VFX resin for rituals | J4: Dropped on harvest.
A5: OUT_MIRTHPETAL_BUNDLE | B5: MIRTHPETAL | C5: Mirthpetal Bundle | D5: 2 | E5: Bundle | F5: Charm: Mirth set | G5: Charms | H5: 3 | I5: Potion: Joy Draft (Bond gain +) | J5: Pairs well with Tricksters.
A6: OUT_FORGETME_PETAL | B6: FORGETMEBUD | C6: Memory Petal | D6: 1 | E6: Item | F6: Ritual: Memory Circle (+Grace) | G6: Rituals | H6: 4 | I6: Charm: Memory Locket | J6: Stacks for Grace multipliers.
A7: OUT_ASHBLOSSOM_PETAL | B7: ASHBLOSSOM | C7: Ash Petal | D7: 1 | E7: Item | F7: Alchemy (Essence distill) | G7: Potions | H7: 3 | I7: Ritual: Cleansing | J7: Synergy with Remains.
A8: OUT_ASH_SHARD | B8: ASHBLOSSOM | C8: Ash Shard | D8: 1 | E8: Item | F8: High-tier Charm core | G8: Charms | H8: 8 | I8: Sell for Tokens | J8: Rare proc on harvest.
A9: OUT_ECTOFRUIT | B9: ECTOFRUIT | C9: Ectofruit | D9: 1 | E9: Consumable | F9: Instant 100% Appetite restoration | G9: Appetite System | H9: 6 | I9: Potion: Radiant Sap | J9: Only from fertilize proc; single-use.
A10: OUT_KINDLE_FREND | B10: KINDLEFERN | C10: Kindle Frond | D10: 2 | E10: Item | F10: Ritual incense, +Grace aura | G10: Rituals | H10: 3 | I10: Potion: Warm Draught | J10: Boosts neighbor Ectofruit chance.
A11: OUT_LAMENT_NECTAR | B11: LAMENT_LILY | C11: Lily Nectar | D11: 1 | E11: Vial | F11: Potion: Lullaby Mist | G11: Potions | H11: 4 | I11: Decor: Sleep Sachet | J11: Good for long nights.
A12: OUT_WRAITH_RESIN | B12: WRAITHVINE | C12: Wraith Resin | D12: 1 | E12: Item | F12: Potion: Shadowguard / high-tier | G12: Potions | H12: 10 | I12: Charm: Nightwatcher | J12: Risky to farm.
A13: OUT_PEACE_PETAL | B13: PEACEBUD | C13: Peace Petal | D13: 1 | E13: Relic | F13: Permanent +1 Contentment cap | G13: Meta/Grace | H13: 0 | I13: One-time relic | J13: Triggers Festival visuals.

Sheet Globals
A1: Parameter | B1: Value | C1: Notes
A2: growth_tick_seconds | B2: 10 | C2: Seconds per plant growth tick
A3: hours_active_per_day | B3: 12 | C3: Hours with growth/day
A4: base_ectofruit_chance | B4: 0.03 | C4: Base proc chance for Ectofruit
A5: fertilize_bonus_per_stack | B5: 0.02 | C5: Chance increase per fertilize stack
A6: fertilize_stacks | B6: 3 | C6: # of fertilize applications
A7: harmony_multiplier | B7: 1 | C7: Multiplier for harmony effects (1=baseline)
A8: fertilized_flag | B8: 1 | C8: 1=Fertilized, 0=Not fertilized
A9: token_value_per_essence | B9: 0.5 | C9: Token value of 1 Essence
A10: token_value_per_remain | B10: 3 | C10: Token value of 1 Remain
A11: token_value_per_timber | B11: 0.25 | C11: Token value per 1 Timber (economy wiring)
A12: token_value_per_rock | B12: 0.35 | C12: Token value per 1 Rock (economy wiring)

Sheet Computed_Metrics
A1: Computed Metrics — Garden of Rest | B1: Formula (Excel) | C1: Value
A2: Ticks per Day | B2: =(3600/Globals!B2)*Globals!B3 -> 4320
A3: Ectofruit Proc Chance (given stacks) | B3: =IF(Globals!B7=0,0,MIN(1,Globals!B3 + Globals!B4*Globals!B5)) -> 1
A4: Expected Ectofruit per Day (per bed) | B4: =Globals!B6*(3600/Globals!B2*Globals!B3)*IF(Globals!B7=0,0,MIN(1,Globals!B3 + Globals!B4*Globals!B5)) -> 12960
A7: PlantID | B7: BaseChance | C7: FertilizeBonus | D7: FertilizeStacks | E7: Fertilized(0/1) | F7: GrowthTickSec | G7: HoursActive | H7: TicksPerDay | I7: ProcChance | J7: ExpEctofruit/Day | K7: Notes
A8: WHISPERBLOOM | B8: 0.05 | C8: 0.03 | D8: 3 | E8: 1 | F8: =Globals!B2 -> 10 | G8: =Globals!B3 -> 12 | H8: =(3600/Globals!B2)*Globals!B3 -> 4320 | I8: =IF(E3=0,0,MIN(1,B3 + C3*D3)) -> 0 | J8: =H3*I3*Globals!B6 -> 0 | K8: Soothing bloom
A9: GRIEFROOT | B9: 0.03 | C9: 0.02 | D9: 3 | E9: 1 | F9: =Globals!B2 -> 10 | G9: =Globals!B3 -> 12 | H9: =(3600/Globals!B2)*Globals!B3 -> 4320 | I9: =IF(E4=0,0,MIN(1,B4 + C4*D4)) -> 0 | J9: =H4*I4*Globals!B6 -> 0 | K9: Grows faster near unhappy ghosts
A10: MIRTHPETAL | B10: 0.04 | C10: 0.02 | D10: 3 | E10: 1 | F10: =Globals!B2 -> 10 | G10: =Globals!B3 -> 12 | H10: =(3600/Globals!B2)*Globals!B3 -> 4320 | I10: =IF(E5=0,0,MIN(1,B5 + C5*D5)) -> 0 | J10: =H5*I5*Globals!B6 -> 0 | K10: Bond booster
A11: FORGETMEBUD | B11: 0.02 | C11: 0.01 | D11: 2 | E11: 1 | F11: =Globals!B2 -> 10 | G11: =Globals!B3 -> 12 | H11: =(3600/Globals!B2)*Globals!B3 -> 4320 | I11: =IF(E6=0,0,MIN(1,B6 + C6*D6)) -> 0 | J11: =H6*I6*Globals!B6 -> 0 | K11: Grace trickle
A12: ASHBLOSSOM | B12: 0 | C12: 0 | D12: 0 | E12: 1 | F12: =Globals!B2 -> 10 | G12: =Globals!B3 -> 12 | H12: =(3600/Globals!B2)*Globals!B3 -> 4320 | I12: =0 -> 0 | J12: =0 -> 0 | K12: No Ectofruit; yields Essence/Remains
A13: KINDLEFERN | B13: 0.03 | C13: 0.02 | D13: 3 | E13: 1 | F13: =Globals!B2 -> 10 | G13: =Globals!B3 -> 12 | H13: =(3600/Globals!B2)*Globals!B3 -> 4320 | I13: =IF(E8=0,0,MIN(1,B8 + C8*D8)) -> 0.14 | J13: =H8*I8*Globals!B6 -> 0 | K13: Grace + Ectofruit synergy
A14: LAMENT_LILY | B14: 0.02 | C14: 0.01 | D14: 2 | E14: 1 | F14: =Globals!B2 -> 10 | G14: =Globals!B3 -> 12 | H14: =(3600/Globals!B2)*Globals!B3 -> 4320 | I14: =IF(E9=0,0,MIN(1,B9 + C9*D9)) -> 0.09 | J14: =H9*I9*Globals!B6 -> 0 | K14: Sleep support
A18: SeedID | B18: Produces PlantID | C18: Token Cost | D18: Essence Cost | E18: Remains Cost | F18: Value/Harvest (Tokens) | G18: Est. Harvests/Day | H18: Est. Token ROI/Day | I18: Notes
A19: SEED_WHISPERBLOOM | B19: WHISPERBLOOM | C19: 1 | D19: 10 | E19: 0 | F19: =SUMPRODUCT((Garden_Outputs!$B$2:$B$13="WHISPERBLOOM")*(Garden_Outputs!$D$2:$D$13)*(Garden_Outputs!$H$2:$H$13)) -> 4 | G19: 1 | H19: =F3*G3 - (C3 + D3*Globals!B8 + E3*Globals!B9) -> 0 | I19: Adjust Harvests/Day as you tune growth & bed count.
A20: SEED_GRIEFROOT | B20: GRIEFROOT | C20: 2 | D20: 12 | E20: 0 | F20: =SUMPRODUCT((Garden_Outputs!$B$2:$B$13="GRIEFROOT")*(Garden_Outputs!$D$2:$D$13)*(Garden_Outputs!$H$2:$H$13)) -> 9 | G20: 1 | H20: =F4*G4 - (C4 + D4*Globals!B8 + E4*Globals!B9) -> 0 | I20: Adjust Harvests/Day as you tune growth & bed count.
A21: SEED_MIRTHPETAL | B21: MIRTHPETAL | C21: 1 | D21: 8 | E21: 0 | F21: =SUMPRODUCT((Garden_Outputs!$B$2:$B$13="MIRTHPETAL")*(Garden_Outputs!$D$2:$D$13)*(Garden_Outputs!$H$2:$H$13)) -> 6 | G21: 1 | H21: =F5*G5 - (C5 + D5*Globals!B8 + E5*Globals!B9) -> 0 | I21: Adjust Harvests/Day as you tune growth & bed count.
A22: SEED_FORGETMEBUD | B22: FORGETMEBUD | C22: 2 | D22: 15 | E22: 0 | F22: =SUMPRODUCT((Garden_Outputs!$B$2:$B$13="FORGETMEBUD")*(Garden_Outputs!$D$2:$D$13)*(Garden_Outputs!$H$2:$H$13)) -> 4 | G22: 1 | H22: =F6*G6 - (C6 + D6*Globals!B8 + E6*Globals!B9) -> 0 | I22: Adjust Harvests/Day as you tune growth & bed count.
A23: SEED_ASHBLOSSOM | B23: ASHBLOSSOM | C23: 0 | D23: 0 | E23: 1 | F23: =SUMPRODUCT((Garden_Outputs!$B$2:$B$13="ASHBLOSSOM")*(Garden_Outputs!$D$2:$D$13)*(Garden_Outputs!$H$2:$H$13)) -> 11 | G23: 1 | H23: =F7*G7 - (C7 + D7*Globals!B8 + E7*Globals!B9) -> #VALUE! | I23: Adjust Harvests/Day as you tune growth & bed count.
A24: SEED_KINDLEFERN | B24: KINDLEFERN | C24: 1 | D24: 10 | E24: 0 | F24: =SUMPRODUCT((Garden_Outputs!$B$2:$B$13="KINDLEFERN")*(Garden_Outputs!$D$2:$D$13)*(Garden_Outputs!$H$2:$H$13)) -> 6 | G24: 1 | H24: =F8*G8 - (C8 + D8*Globals!B8 + E8*Globals!B9) -> 116.47 | I24: Adjust Harvests/Day as you tune growth & bed count.
A25: SEED_LAMENT_LILY | B25: LAMENT_LILY | C25: 1 | D25: 10 | E25: 0 | F25: =SUMPRODUCT((Garden_Outputs!$B$2:$B$13="LAMENT_LILY")*(Garden_Outputs!$D$2:$D$13)*(Garden_Outputs!$H$2:$H$13)) -> 4 | G25: 1 | H25: =F9*G9 - (C9 + D9*Globals!B8 + E9*Globals!B9) -> 116.48 | I25: Adjust Harvests/Day as you tune growth & bed count.
A26: SEED_WRAITHVINE | B26: WRAITHVINE | C26: 0 | D26: 0 | E26: 3 | F26: =SUMPRODUCT((Garden_Outputs!$B$2:$B$13="WRAITHVINE")*(Garden_Outputs!$D$2:$D$13)*(Garden_Outputs!$H$2:$H$13)) -> 10 | G26: 1 | H26: =F10*G10 - (C10 + D10*Globals!B8 + E10*Globals!B9) -> 116.48 | I26: Adjust Harvests/Day as you tune growth & bed count.
A27: SEED_PEACEBUD | B27: PEACEBUD | C27: 0 | D27: 0 | E27: 0 | F27: =SUMPRODUCT((Garden_Outputs!$B$2:$B$13="PEACEBUD")*(Garden_Outputs!$D$2:$D$13)*(Garden_Outputs!$H$2:$H$13)) -> 0 | G27: 1 | H27: =F11*G11 - (C11 + D11*Globals!B8 + E11*Globals!B9) -> 117.49 | I27: Adjust Harvests/Day as you tune growth & bed count.
