Workbook

Sheet Overview
A1: Field | B1: Description
A2: System Name | B2: Building & Construction System
A3: Tagline | B3: Build comfort, craft progress — your sanctuary in wood, stone, and candlelight.
A4: Purpose | B4: Define structures, tiers, HP/repair loops, upgrade costs, and visual progress that anchor every other system.
A5: One‑line Summary | B5: Place and upgrade stations that produce resources, stabilize mood, and unlock systems; keep them repaired as ghosts (and time) wear them down.
A6: Core Loop | B6: Plan → Place → Build → Use (Throughput/Comfort) → Wear/Repair → Upgrade (Tier) → Expand
A7: Key Systems Touched | B7: Tasks (Stations), Garden, Potions/Relics, Rituals, Manifest/Contagion, Lighting, Save/Load, Requests
A8: Out of Scope (v1) | B8: Grid-free terrain deformation, physics-based destruction, multistory/vertical construction.
A9: Success Criteria | B9: • Costs & build times feel fair • HP/repair loops are readable • Upgrades are meaningful • Visual progress is satisfying
A10: Author | B10: Brandon (Caretaker Designer)
A11: Version | B11: 1.0
A12: Last Updated | B12: 2025-11-01 03:19 UTC

Sheet Core_Loop
A1: Phase | B1: Name | C1: What Happens | D1: Rules | E1: UX Cues
A2: 1 | B2: Plan | C2: Pick structure from build menu; preview placement and cost. | D2: Ghost pathing and light coverage matter. | E2: Ghost routes, lantern rings, and cost tooltip.
A3: 2 | B3: Place | C3: Confirm location; pay resource cost; spawn scaffold. | D3: Respect navmesh, clearance, and forbidden zones. | E3: Snap grid + invalid highlights.
A4: 3 | B4: Build | C4: Assigned Builder ghosts construct over time. | D4: Throughput scales with Bond/Temperament; multiple workers help. | E4: Progress bar; hammer VFX; SFX loop.
A5: 4 | B5: Use | C5: Stations run; comfort/lighting applies; storage grows. | D5: Production has queues; some need assigned roles. | E5: Station UI with queues and tooltips.
A6: 5 | B6: Wear/Repair | C6: HP decays (small) and suffers Unrest damage. | D6: Repairs cost Timber/Rock; Janitor fixes minor damage. | E6: Cracks decals; repair prompt.
A7: 6 | B7: Upgrade | C7: Tier up to improve throughput/comfort. | D7: Higher costs; sometimes Tokens/Medallions needed. | E7: VFX burst; mesh variant; banner text.
A8: 7 | B8: Expand | C8: Unlock new zones; place more structures. | D8: Soft caps via Harmony/Mementos/Grace. | E8: Map gates and progress milestones.

Sheet Structures_Catalog
A1: StructureID | B1: Display Name | C1: Role | D1: Category | E1: Footprint
A2: ALTAR | B2: Ritual Altar | C2: Perform rituals; center of Grace production. | D2: Comfort/Meta | E2: 3x3
A3: SAWMILL | B3: Sawmill | C3: Produce Timber from time & worker. | D3: Station/Throughput | E3: 3x3
A4: QUARRY | B4: Quarry | C4: Produce Rock over time. | D4: Station/Throughput | E4: 3x3
A5: WORKSHOP | B5: Workshop | C5: Refine Timber→Boards, Rock→Bricks. | D5: Station/Refine | E5: 3x3
A6: RELIC_FORGE | B6: Relic Forge | C6: Craft Charms from fragments. | D6: Station/Crafting | E6: 3x3
A7: ALCHEMY | B7: Alchemy Table | C7: Brew Potions from Essence/Herbs. | D7: Station/Crafting | E7: 3x2
A8: GARDEN_BED | B8: Garden Bed | C8: Plant flowers tied to spirits. | D8: Comfort/Production | E8: 2x2
A9: COMPOSTER | B9: Composter | C9: Convert Ectoplasm → Fertilizer charges. | D9: Station/Utility | E9: 2x2
A10: LANTERN | B10: Lantern | C10: Calm aura; dampen contagion; night boost. | D10: Comfort/Light | E10: 1x1
A11: GREENHOUSE | B11: Greenhouse | C11: Garden growth boost + rot resistance. | D11: Station/Utility | E11: 3x2
A12: WARDED | B12: Warded Chamber | C12: Cure Afflictions over time. | D12: Station/Healing | E12: 3x2
A13: STORAGE | B13: Storage | C13: Increases resource caps. | D13: Utility/Storage | E13: 2x2

Sheet Tiers_Upgrades
A1: StructureID | B1: Tier | C1: Cost (raw) | D1: Benefits | E1: Visual Notes
A2: ALTAR | B2: 1 | C2: Essence:0, Remains:0, Tokens:0 | D2: Base ritual set | E2: Default
A3: ALTAR | B3: 2 | C3: Essence:30, Remains:8, Tokens:10 | D3: +1 ritual slot; +10% Grace | E3: Mesh/trim swap
A4: ALTAR | B4: 3 | C4: Essence:60, Remains:16, Tokens:20, Medallion:1 | D4: +1 ritual slot; mishap ↓ | E4: Lanterns on frame
A5: SAWMILL | B5: 1 | C5: Timber:10, Rock:6 | D5: Produce Timber | E5: Basic
A6: SAWMILL | B6: 2 | C6: Timber:20, Rock:12, Tokens:5 | D6: Throughput +25% | E6: Bigger wheel
A7: SAWMILL | B7: 3 | C7: Timber:30, Rock:18, Tokens:10 | D7: Throughput +25% | E7: Covered roof
A8: QUARRY | B8: 1 | C8: Timber:8, Rock:8 | D8: Produce Rock | E8: Basic
A9: QUARRY | B9: 2 | C9: Timber:16, Rock:14, Tokens:5 | D9: Throughput +25% | E9: Scaffold
A10: QUARRY | B10: 3 | C10: Timber:24, Rock:20, Tokens:10 | D10: Throughput +25% | E10: Crane

Sheet HP_Repair
A1: StructureID | B1: HP_Max | C1: Wear_perDay | D1: Notes | E1: Repair_Cost
A2: ALTAR | B2: 100 | C2: 0.1 | D2: Per day wear | E2: Essence:0, Timber:2
A3: SAWMILL | B3: 120 | C3: 0.2 | D3: Wear + Unrest hits | E3: Timber:2, Rock:1
A4: QUARRY | B4: 130 | C4: 0.2 | D4: Wear + Unrest hits | E4: Timber:1, Rock:2
A5: WORKSHOP | B5: 120 | C5: 0.15 | D5: Wear | E5: Timber:2, Rock:2
A6: RELIC_FORGE | B6: 100 | C6: 0.15 | D6: Wear | E6: Timber:1, Rock:1
A7: ALCHEMY | B7: 100 | C7: 0.15 | D7: Wear | E7: Timber:1, Rock:1
A8: GARDEN_BED | B8: 80 | C8: 0.1 | D8: Trample risk | E8: Timber:1
A9: COMPOSTER | B9: 90 | C9: 0.1 | D9: Wear | E9: Timber:1, Rock:1
A10: LANTERN | B10: 60 | C10: 0.05 | D10: Bulb replace | E10: Tokens:1
A11: GREENHOUSE | B11: 110 | C11: 0.1 | D11: Rot protection | E11: Timber:2, Rock:2
A12: WARDED | B12: 110 | C12: 0.1 | D12: Healing use | E12: Timber:2, Rock:2
A13: STORAGE | B13: 100 | C13: 0.1 | D13: Wear | E13: Timber:1, Rock:1

Sheet Placement_Pathing
A1: Rule | B1: Default/Value | C1: Notes
A2: GridSize | B2: 1m per cell | C2: All footprints align to grid (1x1,2x2,3x3).
A3: Clearance | B3: 0.5m border | C3: No overlap; leave aisles for ghosts.
A4: Navmesh | B4: Walkable required | C4: No blocking main routes to Altar/Garden.
A5: Forbidden Zones | B5: Gate/Extraction/Edge | C5: No placement near gates or map edges.
A6: Light Coverage | B6: LANTERN radii | C6: Show rings to cover sleep zones and workstations.
A7: Proximity Buffs | B7: Storyteller near beds | C7: Some combos (Storyteller+Garden) add small bonuses.

Sheet Station_Throughput
A1: StructureID | B1: Metric | C1: Base | D1: Tier Bonus | E1: Notes
A2: SAWMILL | B2: Timber/hr | C2: 2 | D2: +25% per tier | E2: RoleFit × Bond × Harmony
A3: QUARRY | B3: Rock/hr | C3: 2 | D3: +25% per tier | E3: RoleFit × Bond × Harmony
A4: WORKSHOP_BOARDS | B4: Boards/hr | C4: 1 | D4: +20% per tier | E4: Consumes Timber
A5: WORKSHOP_BRICKS | B5: Bricks/hr | C5: 1 | D5: +20% per tier | E5: Consumes Rock
A6: RELIC_FORGE | B6: Charms/hr | C6: 0.25 | D6: +10% per tier | E6: Consumes Fragments/Essence/Remains
A7: ALCHEMY | B7: Potions/hr | C7: 0.4 | D7: +10% per tier | E7: Consumes Essence/Herbs/Ectoplasm
A8: COMPOSTER | B8: Fertilizer/hr | C8: 0.5 | D8: +10% per tier | E8: Consumes Ectoplasm
A9: STORAGE | B9: Cap increase | C9: 25 | D9: +25 per tier | E9: All resource caps
A10: LANTERN | B10: Calm radius m | C10: 3 | D10: +1m per tier | E10: Dampens contagion; night boost
A11: WARDED | B11: Afflictions/day | C11: 0.5 | D11: +25% per tier | E11: Slots × Tier
A12: GREENHOUSE | B12: Growth bonus | C12: 0.15 | D12: +0.10 per tier | E12: Garden growth × (1+bonus)

Sheet Visual_Progress
A1: StructureID | B1: Tier Visuals
A2: ALTAR | B2: T1 plain stones → T2 engraved trim → T3 shrine with lanterns.
A3: SAWMILL | B3: T1 wheel → T2 protected gear → T3 roof + banners.
A4: QUARRY | B4: T1 simple pit → T2 scaffold → T3 crane & pulley.
A5: WORKSHOP | B5: T1 bench → T2 table + tools → T3 full bench & rack.
A6: RELIC_FORGE | B6: T1 stand → T2 mirror shard → T3 bone adornments.
A7: ALCHEMY | B7: T1 table → T2 tubes → T3 flask rack & heater.
A8: GARDEN_BED | B8: T1 stones → T2 fence → T3 lantern stake.
A9: COMPOSTER | B9: T1 bin → T2 lid + vent → T3 crank & meter.
A10: LANTERN | B10: T1 post → T2 double flame → T3 halo crown.
A11: GREENHOUSE | B11: T1 frame → T2 panes → T3 warm glow.
A12: WARDED | B12: T1 cot → T2 runes → T3 sealed door.
A13: STORAGE | B13: T1 chest → T2 rack → T3 warehouse.

Sheet Hooks
A1: Hook ID | B1: Context / Feature | C1: Unity Component / Script | D1: Key Fields / Serialized Props | E1: Events (Invoke/Listen) | F1: Triggered By | G1: Emits / Subscribes To | H1: Expected Prefab / Asset | I1: Notes / Integration
A2: HK_BuildMenu | B2: Build menu orchestration | C2: KD.Build.Menu | D2: catalog[], costs{}, grid, ghostPaths | E2: OnOpen, OnSelect, OnConfirm | F2: Player input | G2: Emit: BuildRequested | H2: UI_BuildMenu | I2: Filters by unlocks; shows rings/costs.
A3: HK_Placer | B3: Placement + preview | C3: KD.Build.Placer | D3: footprint, clearance, validMask | E3: OnMove, OnRotate, OnConfirm | F3: Player move | G3: Emit: PlaceStructure | H3: Ghost path hinting; snap grid.
A4: HK_BuildQueue | B4: Construction queue | C4: KD.Build.Queue | D4: jobs[], workers[], speedMult | E4: OnJobAdded, OnJobProgress, OnJobDone | F4: Player/Stations | G4: Emit: Progress, Done | H4: Supports multi-worker speed.
A5: HK_Station | B5: Station controller | C5: KD.Stations.Controller | D5: tier, hp, wear, throughput | E5: OnTick, OnUse, OnDamage | F5: Time/Events | G5: Emit: Output, Damaged | H5: Base class for all stations.
A6: HK_Repair | B6: Repair interaction | C6: KD.Build.Repair | D6: costs{}, time | E6: OnRepairStart, OnRepairDone | F6: Player/Janitor | G6: Emit: Repaired | H6: Consumes resources; heals HP.
A7: HK_Upgrade | B7: Upgrade flow | C7: KD.Build.Upgrade | D7: nextTier, cost{}, visuals | E7: OnUpgradeConfirm, OnUpgradeComplete | F7: Player/Grace unlock | G7: Emit: Upgraded | H7: Swaps meshes/materials.

Sheet Tuning_Defaults
A1: Parameter | B1: Default | C1: Min | D1: Max | E1: Notes
A2: build_time_base_sec | B2: 45 | C2: 20 | D2: 120 | E2: Base time for 3x3 (scaled by footprint).
A3: multiworker_bonus | B3: 0.2 | C3: 0.1 | D3: 0.4 | E3: Per worker after the first (additive).
A4: hp_decay_per_day | B4: 0.02 | C4: 0 | D4: 0.05 | E4: Passive HP wear fraction/day.
A5: unrest_damage_hit | B5: 0.1 | C5: 0.05 | D5: 0.25 | E5: HP fraction lost on Unrest vandalism.
A6: repair_speed_mult | B6: 1 | C6: 0.5 | D6: 2 | E6: Multiplier for repair pace.
A7: path_clearance_m | B7: 0.5 | C7: 0.25 | D7: 1 | E7: Path clearance margin.
A8: lantern_radius_t1 | B8: 3 | C8: 2 | D8: 5 | E8: Lantern calm zone at T1.
A9: lantern_radius_per_tier | B9: 1 | C9: 0.5 | D9: 2 | E9: Meters added per tier.
A10: station_queue_limit | B10: 3 | C10: 1 | D10: 5 | E10: Max jobs queued per station at T1.
A11: upgrade_token_cost_scale | B11: 1 | C11: 0.5 | D11: 2 | E11: Scale factor applied to tokens at higher tiers.

Sheet External_Links
A1: LinkKey | B1: Excel_Formula | C1: Notes
A2: Token_Token_Value | B2: 0 | C2: Token face value
A3: Timber_Token_Value | B3: 0 | C3: Token per Timber
A4: Rock_Token_Value | B4: 0 | C4: Token per Rock
A5: Boards_Token_Value (proxy) | B5: 0 | C5: Proxy from Resources sheet base value
A6: Bricks_Token_Value (proxy) | B6: 0 | C6: Proxy from Resources sheet base value

Sheet Computed_Metrics
A1: Metric | B1: Formula (Excel) | C1: Var1 | D1: Var2 | E1: Var3 | F1: Var4 | G1: Var5 | H1: Var6
A2: Build Time (sec) | B2: 0 | C2: FootprintScale | D2: Workers | E2: build_time_base_sec | F2: multiworker_bonus
A3: Repair Cost (Tokens) | B3: 0 | C3: TimberCost | D3: RockCost | E3: TokenCost
A4: Station Throughput (per hr) | B4: 0 | C4: Base | D4: TierBonus | E4: Tier | F4: RoleFit | G4: Bond | H4: Harmony
A5: Lantern Radius (m) | B5: 0 | C5: Tier | D5: lantern_radius_t1 | E5: lantern_radius_per_tier

Sheet Build_Planner
A1: StructureID | B1: Tier | C1: Count | D1: TimberCost | E1: RockCost | F1: TokenCost | G1: Medallions | H1: FootprintScale | I1: WorkersPerJob | J1: BuildTime_Sec | K1: Total_Tokens
A2: SAWMILL | B2: 1 | C2: 1 | D2: 10 | E2: 6 | F2: 0 | G2: 0 | H2: 9 | I2: 1 | J2: =Tuning_Defaults!B2 * H2 / (1 + (I2-1)*Tuning_Defaults!B3) * C2 -> 0 | K2: =D2*External_Links!B2 + E2*External_Links!B3 + F2*External_Links!B1 + G2*25 -> 0
A3: QUARRY | B3: 1 | C3: 1 | D3: 8 | E3: 8 | F3: 0 | G3: 0 | H3: 9 | I3: 1 | J3: =Tuning_Defaults!B2 * H3 / (1 + (I3-1)*Tuning_Defaults!B3) * C3 -> 0 | K3: =D3*External_Links!B2 + E3*External_Links!B3 + F3*External_Links!B1 + G3*25 -> 0
A4: WORKSHOP | B4: 1 | C4: 1 | D4: 12 | E4: 12 | F4: 0 | G4: 0 | H4: 9 | I4: 1 | J4: =Tuning_Defaults!B2 * H4 / (1 + (I4-1)*Tuning_Defaults!B3) * C4 -> 0 | K4: =D4*External_Links!B2 + E4*External_Links!B3 + F4*External_Links!B1 + G4*25 -> 0
A5: RELIC_FORGE | B5: 1 | C5: 0 | D5: 6 | E5: 4 | F5: 0 | G5: 0 | H5: 9 | I5: 1 | J5: =Tuning_Defaults!B2 * H5 / (1 + (I5-1)*Tuning_Defaults!B3) * C5 -> 0 | K5: =D5*External_Links!B2 + E5*External_Links!B3 + F5*External_Links!B1 + G5*25 -> 0
A6: ALCHEMY | B6: 1 | C6: 0 | D6: 6 | E6: 4 | F6: 0 | G6: 0 | H6: 6 | I6: 1 | J6: =Tuning_Defaults!B2 * H6 / (1 + (I6-1)*Tuning_Defaults!B3) * C6 -> 0 | K6: =D6*External_Links!B2 + E6*External_Links!B3 + F6*External_Links!B1 + G6*25 -> 0
A7: GARDEN_BED | B7: 1 | C7: 2 | D7: 2 | E7: 0 | F7: 0 | G7: 0 | H7: 4 | I7: 1 | J7: =Tuning_Defaults!B2 * H7 / (1 + (I7-1)*Tuning_Defaults!B3) * C7 -> 0 | K7: =D7*External_Links!B2 + E7*External_Links!B3 + F7*External_Links!B1 + G7*25 -> 0
A8: COMPOSTER | B8: 1 | C8: 1 | D8: 2 | E8: 2 | F8: 0 | G8: 0 | H8: 4 | I8: 1 | J8: =Tuning_Defaults!B2 * H8 / (1 + (I8-1)*Tuning_Defaults!B3) * C8 -> 0 | K8: =D8*External_Links!B2 + E8*External_Links!B3 + F8*External_Links!B1 + G8*25 -> 0
A9: LANTERN | B9: 1 | C9: 3 | D9: 0 | E9: 0 | F9: 1 | G9: 0 | H9: 1 | I9: 1 | J9: =Tuning_Defaults!B2 * H9 / (1 + (I9-1)*Tuning_Defaults!B3) * C9 -> 0 | K9: =D9*External_Links!B2 + E9*External_Links!B3 + F9*External_Links!B1 + G9*25 -> 0
A10: GREENHOUSE | B10: 1 | C10: 0 | D10: 12 | E10: 12 | F10: 0 | G10: 0 | H10: 6 | I10: 1 | J10: =Tuning_Defaults!B2 * H10 / (1 + (I10-1)*Tuning_Defaults!B3) * C10 -> 0 | K10: =D10*External_Links!B2 + E10*External_Links!B3 + F10*External_Links!B1 + G10*25 -> 0
A11: WARDED | B11: 1 | C11: 0 | D11: 12 | E11: 12 | F11: 0 | G11: 0 | H11: 6 | I11: 1 | J11: =Tuning_Defaults!B2 * H11 / (1 + (I11-1)*Tuning_Defaults!B3) * C11 -> 0 | K11: =D11*External_Links!B2 + E11*External_Links!B3 + F11*External_Links!B1 + G11*25 -> 0
A12: STORAGE | B12: 1 | C12: 1 | D12: 6 | E12: 6 | F12: 0 | G12: 0 | H12: 4 | I12: 1 | J12: =Tuning_Defaults!B2 * H12 / (1 + (I12-1)*Tuning_Defaults!B3) * C12 -> 0 | K12: =D12*External_Links!B2 + E12*External_Links!B3 + F12*External_Links!B1 + G12*25 -> 0
A13: ALTAR | B13: 1 | C13: 1 | D13: 0 | E13: 0 | F13: 0 | G13: 0 | H13: 9 | I13: 1 | J13: =Tuning_Defaults!B2 * H13 / (1 + (I13-1)*Tuning_Defaults!B3) * C13 -> 0 | K13: =D13*External_Links!B2 + E13*External_Links!B3 + F13*External_Links!B1 + G13*25 -> 0

Sheet Repair_Budget
A1: StructureID | B1: Count | C1: HP_Max | D1: Wear_perDay | E1: UnrestHits_perDay | F1: TimberCostRepair | G1: RockCostRepair | H1: TokenCostRepair | I1: HP_Loss_perDay | J1: Repair_Tokens_perDay
A2: SAWMILL | B2: 1 | C2: 120 | D2: 0.2 | E2: 0 | F2: 2 | G2: 1 | H2: 0 | I2: =C2*D2*B2 + C2*B2*E2*Tuning_Defaults!B4 -> 0 | J2: =(F2*External_Links!B2 + G2*External_Links!B3 + H2*External_Links!B1) * B2 -> 0
A3: QUARRY | B3: 1 | C3: 130 | D3: 0.2 | E3: 0 | F3: 1 | G3: 2 | H3: 0 | I3: =C3*D3*B3 + C3*B3*E3*Tuning_Defaults!B4 -> 0 | J3: =(F3*External_Links!B2 + G3*External_Links!B3 + H3*External_Links!B1) * B3 -> 0
A4: WORKSHOP | B4: 1 | C4: 120 | D4: 0.15 | E4: 0 | F4: 2 | G4: 2 | H4: 0 | I4: =C4*D4*B4 + C4*B4*E4*Tuning_Defaults!B4 -> 0 | J4: =(F4*External_Links!B2 + G4*External_Links!B3 + H4*External_Links!B1) * B4 -> 0
A5: RELIC_FORGE | B5: 0 | C5: 100 | D5: 0.15 | E5: 0 | F5: 1 | G5: 1 | H5: 0 | I5: =C5*D5*B5 + C5*B5*E5*Tuning_Defaults!B4 -> 0 | J5: =(F5*External_Links!B2 + G5*External_Links!B3 + H5*External_Links!B1) * B5 -> 0
A6: ALCHEMY | B6: 0 | C6: 100 | D6: 0.15 | E6: 0 | F6: 1 | G6: 1 | H6: 0 | I6: =C6*D6*B6 + C6*B6*E6*Tuning_Defaults!B4 -> 0 | J6: =(F6*External_Links!B2 + G6*External_Links!B3 + H6*External_Links!B1) * B6 -> 0
A7: GARDEN_BED | B7: 2 | C7: 80 | D7: 0.1 | E7: 0 | F7: 1 | G7: 0 | H7: 0 | I7: =C7*D7*B7 + C7*B7*E7*Tuning_Defaults!B4 -> 0 | J7: =(F7*External_Links!B2 + G7*External_Links!B3 + H7*External_Links!B1) * B7 -> 0
A8: COMPOSTER | B8: 1 | C8: 90 | D8: 0.1 | E8: 0 | F8: 1 | G8: 1 | H8: 0 | I8: =C8*D8*B8 + C8*B8*E8*Tuning_Defaults!B4 -> 0 | J8: =(F8*External_Links!B2 + G8*External_Links!B3 + H8*External_Links!B1) * B8 -> 0
A9: LANTERN | B9: 3 | C9: 60 | D9: 0.05 | E9: 0 | F9: 0 | G9: 0 | H9: 1 | I9: =C9*D9*B9 + C9*B9*E9*Tuning_Defaults!B4 -> 0 | J9: =(F9*External_Links!B2 + G9*External_Links!B3 + H9*External_Links!B1) * B9 -> 0
A10: GREENHOUSE | B10: 0 | C10: 110 | D10: 0.1 | E10: 0 | F10: 2 | G10: 2 | H10: 0 | I10: =C10*D10*B10 + C10*B10*E10*Tuning_Defaults!B4 -> 0 | J10: =(F10*External_Links!B2 + G10*External_Links!B3 + H10*External_Links!B1) * B10 -> 0
A11: WARDED | B11: 0 | C11: 110 | D11: 0.1 | E11: 0 | F11: 2 | G11: 2 | H11: 0 | I11: =C11*D11*B11 + C11*B11*E11*Tuning_Defaults!B4 -> 0 | J11: =(F11*External_Links!B2 + G11*External_Links!B3 + H11*External_Links!B1) * B11 -> 0
A12: STORAGE | B12: 1 | C12: 100 | D12: 0.1 | E12: 0 | F12: 1 | G12: 1 | H12: 0 | I12: =C12*D12*B12 + C12*B12*E12*Tuning_Defaults!B4 -> 0 | J12: =(F12*External_Links!B2 + G12*External_Links!B3 + H12*External_Links!B1) * B12 -> 0
A13: ALTAR | B13: 1 | C13: 100 | D13: 0.1 | E13: 0 | F13: 2 | G13: 0 | H13: 0 | I13: =C13*D13*B13 + C13*B13*E13*Tuning_Defaults!B4 -> 0 | J13: =(F13*External_Links!B2 + G13*External_Links!B3 + H13*External_Links!B1) * B13 -> 0

Sheet Station_Dashboard
A1: Station | B1: Tier | C1: RoleFit | D1: Bond | E1: Harmony | F1: Base | G1: TierBonus | H1: Throughput_per_hr | I1: Tokens_per_hr
A2: SAWMILL | B2: 1 | C2: 1 | D2: 1 | E2: 1 | F2: {=_xlfn.XLOOKUP(A2,'Station_Throughput'!$A:$A,'Station_Throughput'!$C:$C,0)} -> 0 | G2: {=VALUE(SUBSTITUTE(_xlfn.XLOOKUP(A2,'Station_Throughput'!$A:$A,'Station_Throughput'!$D:$D,0),"+",""))} -> 0 | H2: =B2 * (1 + C2*A2) * D2 * E2 * F2 -> 0 | I2: =IF(A2="SAWMILL", H2*External_Links!B2, IF(A2="QUARRY", H3*External_Links!B3, IF(A2="WORKSHOP_BOARDS", H4*External_Links!B4, IF(A2="WORKSHOP_BRICKS", H5*External_Links!B5, "—")))) -> 0
A3: QUARRY | B3: 1 | C3: 1 | D3: 1 | E3: 1 | F3: {=_xlfn.XLOOKUP(A3,'Station_Throughput'!$A:$A,'Station_Throughput'!$C:$C,0)} -> 0 | G3: {=VALUE(SUBSTITUTE(_xlfn.XLOOKUP(A3,'Station_Throughput'!$A:$A,'Station_Throughput'!$D:$D,0),"+",""))} -> 0 | H3: =B3 * (1 + C3*A3) * D3 * E3 * F3 -> 0
A4: WORKSHOP_BOARDS | B4: 1 | C4: 1 | D4: 1 | E4: 1 | F4: {=_xlfn.XLOOKUP(A4,'Station_Throughput'!$A:$A,'Station_Throughput'!$C:$C,0)} -> 0 | G4: {=VALUE(SUBSTITUTE(_xlfn.XLOOKUP(A4,'Station_Throughput'!$A:$A,'Station_Throughput'!$D:$D,0),"+",""))} -> 0 | H4: =B4 * (1 + C4*A4) * D4 * E4 * F4 -> 0
A5: WORKSHOP_BRICKS | B5: 1 | C5: 1 | D5: 1 | E5: 1 | F5: {=_xlfn.XLOOKUP(A5,'Station_Throughput'!$A:$A,'Station_Throughput'!$C:$C,0)} -> 0 | G5: {=VALUE(SUBSTITUTE(_xlfn.XLOOKUP(A5,'Station_Throughput'!$A:$A,'Station_Throughput'!$D:$D,0),"+",""))} -> 0 | H5: =B5 * (1 + C5*A5) * D5 * E5 * F5 -> 0
A6: COMPOSTER | B6: 1 | C6: 1 | D6: 1 | E6: 1 | F6: {=_xlfn.XLOOKUP(A6,'Station_Throughput'!$A:$A,'Station_Throughput'!$C:$C,0)} -> 0 | G6: {=VALUE(SUBSTITUTE(_xlfn.XLOOKUP(A6,'Station_Throughput'!$A:$A,'Station_Throughput'!$D:$D,0),"+",""))} -> 0 | H6: =B6 * (1 + C6*A6) * D6 * E6 * F6 -> 0
A7: LANTERN | B7: 1 | C7: 1 | D7: 1 | E7: 1 | F7: {=_xlfn.XLOOKUP(A7,'Station_Throughput'!$A:$A,'Station_Throughput'!$C:$C,0)} -> 0 | G7: {=VALUE(SUBSTITUTE(_xlfn.XLOOKUP(A7,'Station_Throughput'!$A:$A,'Station_Throughput'!$D:$D,0),"+",""))} -> 0 | H7: =B7 * (1 + C7*A7) * D7 * E7 * F7 -> 0
