Workbook

Sheet Overview
A1: Field | B1: Description
A2: System Name | B2: Contentment, Bond & Grace (Meta) System
A3: Tagline | B3: Harmony in, progress out — feelings are your economy.
A4: Purpose | B4: Provide a unified, tunable model for happiness (Contentment), relationships (Bond), and progression (Grace). Balances all care & ritual loops.
A5: One‑line Summary | B5: Daily care raises Contentment and Bonds, which increase Essence/Grace yield; neglect causes Manifest/Unrest; the Daily Harmony score drives pacing and rewards.
A6: Core Loop | B6: Care → Contentment ↑ → Essence ↑ → Rituals → Grace ↑ → Upgrades → Better Care → Repeat
A7: Key Systems Touched | B7: Rituals, Requests, Potions, Garden, Charms, Manifest/Contagion, Mementos, Buildings, Lighting
A8: Out of Scope (v1) | B8: Complex social graphs between ghosts, long-form romance arcs, faction politics.
A9: Success Criteria | B9: • Decay feels fair • Bonds grow predictably • Grace pacing is readable • The Daily Harmony summary feels rewarding and honest
A10: Author | B10: Brandon (Caretaker Designer)
A11: Version | B11: 1.0
A12: Last Updated | B12: 2025-11-01 03:14 UTC

Sheet Core_Flow
A1: Phase | B1: Name | C1: What Happens | D1: Rules | E1: UX Cues
A2: 1 | B2: Morning Check | C2: Feed, soothe, clean; ensure lanterns and garden are ready. | D2: Raise Contentment early; reduce leak risk. | E2: HUD shows low-mood list; Daily target tips.
A3: 2 | B3: Work & Requests | C3: Ghosts perform roles; requests spawn independently. | D3: Bond & mood alter efficiency and request positivity. | E3: Meters on HUD; request toasts.
A4: 3 | B4: Ritual Window | C4: Perform key rituals; spend Essence/Remains for Grace. | D4: Grace pacing determined by harmony; Mishaps if low mood. | E4: Altar panel: costs, effects, cooldowns.
A5: 4 | B5: Evening Stabilize | C5: Clean remaining leaks; rest; Storytime; light lanterns. | D5: Prevents night surges; raises Harmony score. | E5: Daily summary hints for tomorrow.
A6: 5 | B6: Daily Harmony | C6: Score and text summarize outcomes; give small rewards. | D6: Score weights contentment, bond, leaks, requests. | E6: Banner + score + minor rewards (seeds, Mementos trickle).

Sheet Contentment_Model
A1: Parameter | B1: Default | C1: Notes
A2: BaseDecay_perMin | B2: -0.2 | C2: Base Contentment change per minute (negative).
A3: HungerPenalty_mult | B3: 1.25 | C3: When Appetite < AppetiteThreshold, multiply decay magnitude.
A4: AppetiteThreshold | B4: 0.4 | C4: Below this appetite fraction, apply HungerPenalty.
A5: Contagion_magnitude | B5: from Manifest | C5: Driven by contagion model; added to decay.
A6: Lantern_Damp_day | B6: 0.85 | C6: Multiply negative decay inside lantern radius (day).
A7: Lantern_Damp_night | B7: 0.75 | C7: Multiply negative decay inside lantern radius (night).
A8: Aura_Garden_bonus | B8: 0.05 | C8: Per minute bonus while within healthy bloom aura (stack capped).
A9: Charm_Damp | B9: 0.9 | C9: Multiplicative dampening from Calm-type charms.
A10: Request_Buffer | B10: 0.1 | C10: Per completed request that day (stack capped).
A11: Daily_Min_Cap | B11: -2.5 | C11: Floor per-ghost total daily change (prevents spirals).
A12: Daily_Max_Cap | B12: 3 | C12: Ceiling per-ghost total daily change (prevents runaway).

Sheet Bond_Model
A1: Parameter | B1: Default | C1: Notes
A2: BondLevels | B2: 0,1,2,3,4,5 | C2: Max 5 per ghost.
A3: BondXP_perLevel | B3: 3,4,6,9,12 | C3: XP needed to reach next level.
A4: XP_from_Request | B4: 1 | C4: Completing a request grants this XP.
A5: XP_from_Storytime | B5: 0.5 | C5: Per participant at Storytime.
A6: XP_from_Gift | B6: 0.5 | C6: Per small gift (daily cap).
A7: Bond_Decay_idle | B7: 0 | C7: No passive Bond decay (v1).
A8: Bond_Effect_Efficiency | B8: +2% per level | C8: Work output bonus.
A9: Bond_Effect_Stability | B9: -3% mood decay per level | C9: Decay dampening.
A10: Bond_Effect_Resist | B10: -5% contagion per level | C10: Spread resistance.

Sheet Grace_Model
A1: Parameter | B1: Default | C1: Notes
A2: Grace_from_Rituals | B2: per ritual | C2: See Rituals spec; base yields.
A3: Harmony_Grace_Bonus | B3: +0%..+50% | C3: Multiplier based on Daily Harmony tier.
A4: Release_Grace | B4: 5 | C4: Base Grace per peaceful Release.
A5: Release_Bond_Bonus | B5: +1..+3 | C5: Bonus Grace if Bond ≥ 3 (scales).
A6: PerfectDay_Bonus | B6: 2 | C6: If no leaks and avg Contentment ≥ 75%.
A7: Daily_Grace_SoftCap | B7: 20 | C7: Past this, diminishing returns (-25%).
A8: Spend_Target_perDay | B8: 10 | C8: Suggested spend/day (pacing target).

Sheet Daily_Harmony
A1: Element | B1: Value | C1: Notes
A2: Inputs | B2: AvgContentment, LeaksCount, RotCount, RequestsDone, RequestsIgnored, AvgBond, NightSurgesCleansed
A3: ScoreFormula | B3: 0 | C3: 0..100+
A4: TierThresholds | B4: Calm: 80+, Steady: 60–79, Wobbly: 40–59, Frayed: <40 | C4: Used for banner text & bonuses.
A5: TierBonuses | B5: Calm:+50% Grace Bonus, Steady:+25%, Wobbly:+10%, Frayed:0% | C5: Applied next day to ritual Grace only.
A6: BannerText | B6: Calm: “Peace, for now.”; Steady: “We held together.”; Wobbly: “A near thing.”; Frayed: “Barely holding on.” | C6: Localization-friendly strings.

Sheet Interactions
A1: System | B1: Interaction
A2: Rituals | B2: Cleansing/Feast/Release affect C,B,G; Grace pacing derived here.
A3: Requests | B3: Drive Bond XP; produce small Contentment; failure hurts.
A4: Manifest/Contagion | B4: Low mood triggers leaks; drains Contentment; cleanup rewards help.
A5: Garden | B5: Auras stabilize; Ectofruit restores Appetite; Ashblossom yields Essence.
A6: Charms | B6: Calm and Focus reduce decay; Mirth speeds Bond.
A7: Lighting | B7: Lantern radius dampens decay; stronger at night.
A8: Buildings | B8: Beds/rest zones reduce Flicker; stations raise stability.

Sheet Hooks
A1: Hook ID | B1: Context / Feature | C1: Unity Component / Script | D1: Key Fields / Serialized Props | E1: Events (Invoke/Listen) | F1: Triggered By | G1: Emits / Subscribes To | H1: Expected Prefab / Asset | I1: Notes / Integration
A2: HK_ContentmentAgent | B2: Per-ghost mood tick & caps | C2: KD.Mood.ContentmentAgent | D2: decayBase, hungerMult, dampeners[], caps{} | E2: OnTick, OnContentmentChanged | F2: TimeManager, Events | G2: Emit: MoodChanged | H2: — | I2: Centralizes all mood math.
A3: HK_BondAgent | B3: Per-ghost Bond xp & level | C3: KD.Social.BondAgent | D3: level, xp, xpNeed[], effects{} | E3: OnBondGain, OnLevelUp | F3: Requests, Storytime, Gifts | G3: Emit: BondChanged | H3: — | I3: Applies per-level buffs to systems.
A4: HK_GraceBank | B4: Grace earn/spend pacing | C4: KD.Meta.GraceBank | D4: total, softCap, dailyEarn, dailySpend | E4: OnGraceEarned, OnGraceSpent | F4: Rituals, DailyHarmony | G4: Emit: GraceTotals, DaySummary | H4: — | I4: Handles soft caps, next-day bonuses.
A5: HK_HarmonySummary | B5: Daily score & banner | C5: KD.Meta.HarmonySummary | D5: inputs{}, score, tier | E5: OnDayEnd | F5: TimeManager | G5: Emit: HarmonyTier, Bonus | H5: UI_DailyBanner | I5: Grants next-day Grace bonus.

Sheet Tuning_Defaults
A1: Parameter | B1: Default | C1: Min | D1: Max | E1: Notes
A2: base_decay_per_min | B2: -0.2 | C2: -0.5 | D2: -0.1 | E2: Base Contentment change / minute.
A3: hunger_penalty_mult | B3: 1.25 | C3: 1 | D3: 1.5 | E3: When Appetite < threshold.
A4: appetite_threshold | B4: 0.4 | C4: 0.2 | D4: 0.6 | E4: Below this → penalty.
A5: lantern_damp_day | B5: 0.85 | C5: 0.6 | D5: 0.95 | E5: Multiply negative decay in light (day).
A6: lantern_damp_night | B6: 0.75 | C6: 0.5 | D6: 0.95 | E6: Multiply negative decay in light (night).
A7: garden_aura_bonus_per_min | B7: 0.05 | C7: 0.01 | D7: 0.1 | E7: Positive per-minute in garden aura.
A8: request_buffer_per | B8: 0.1 | C8: 0.05 | D8: 0.2 | E8: Per request completed (stack cap 3).
A9: daily_min_cap | B9: -2.5 | C9: -5 | D9: -1 | E9: Floor per-ghost daily total change.
A10: daily_max_cap | B10: 3 | C10: 1 | D10: 5 | E10: Ceiling per-ghost daily total change.
A11: bond_xp_request | B11: 1 | C11: 0.5 | D11: 2 | E11: Bond XP per request.
A12: bond_xp_storytime | B12: 0.5 | C12: 0.25 | D12: 1 | E12: Bond XP per Storytime participant.
A13: bond_xp_gift | B13: 0.5 | C13: 0.25 | D13: 1 | E13: Bond XP per gift (daily cap 1).
... A20: grace_spend_target | B20: 10 | C20: 6 | D20: 20 | E20: Suggested daily spend target.

Sheet External_Links
A1: LinkKey | B1: Excel_Formula | C1: Notes
A2: Essence_Token_Value | B2: 0 | C2: Token value of Essence
A3: Remains_Token_Value | B3: 0 | C3: Token value of Remains
A4: Token_Token_Value | B4: 0 | C4: Face value per Token

Sheet Computed_Metrics
A1: Metric | B1: Formula (Excel) | C1: Var1 | D1: Var2 | E1: Var3 | F1: Var4 | G1: Var5 | H1: Var6
A2: Contentment Δ / Day (per ghost) | B2: 0 | C2: Minutes | D2: LightDamp | E2: HungerMult | F2: GardenBonus | G2: RequestBuffers | H2: BondDecayMod
A3: Bond XP / Day (avg) | B3: 0 | C3: RequestsDone | D3: StoryParticipants | E3: Gifts
A4: Grace / Day (est.) | B4: 0 | C4: RitualGrace | D4: HarmonyBonus | E4: Releases | F4: PerfectDay | G4: Diminish
A5: Harmony Score | B5: 0 | C5: AvgContentment | D5: RequestsDone | E5: Leaks | F5: Rot | G5: Ignored | H5: AvgBond

Sheet Harmony_Inputs
A1: Key | B1: Value | C1: Notes
A2: AvgContentment | B2: 0.75 | C2: 0–1 average across the day
A3: Leaks | B3: 1 | C3: Total leaks today
A4: Rot | B4: 0 | C4: Total rot events today
A5: RequestsDone | B5: 3 | C5: Completed requests
A6: RequestsIgnored | B6: 0 | C6: Ignored/expired requests
A7: AvgBond | B7: 2 | C7: Average bond level across ghosts (0–5)
A8: NightCleansed | B8: 1 | C8: Night surges cleansed
A9: RitualGrace | B9: 6 | C9: Total ritual grace earned today (sum)
A10: HarmonyBonus | B10: 0.25 | C10: 0..0.5 applied to ritual grace only

Sheet External_Data
A1: Key | B1: Excel_Formula | C1: Notes
A2: Requests_ExpectedPerDay | B2: {=IFERROR(_xlfn.XLOOKUP("Expected Requests / Day",'[Follower_Tasks_And_Requests_System_Spec_Wired_LiveAndChart.xlsx]Computed_Metrics_Wired'!$A:$A,'[Follower_Tasks_And_Requests_System_Spec_Wired_LiveAndChart.xlsx]Computed_Metrics_Wired'!$B:$B,0),"")} -> 0 | C2: Opens when Followers sheet is loaded; use this as a reference for RequestsDone target.
A3: Rituals_Grace_Adjusted_Total | B3: =IFERROR(SUM('[Rituals_And_Altar_System_Spec_Wired_WithCharts_Sliders_Threshold_Feast.xlsx]Costs_Live'!$I:$I),"") -> 0 | C3: Sum of Grace_Adjusted column from Costs_Live sheet.

Sheet Harmony_Dashboard
A1: Harmony Dashboard
A2: AvgContentment | B2: {=_xlfn.XLOOKUP("AvgContentment",Harmony_Inputs!$A:$A,Harmony_Inputs!$B:$B,0)} -> 0 | D2: Harmony Score | E2: =ROUND( B2*50 + B5*2 + B8*2 - B3*3 - B4*5 - B6*2 + B7*3 , 0) -> 0
A3: Leaks | B3: {=_xlfn.XLOOKUP("Leaks",Harmony_Inputs!$A:$A,Harmony_Inputs!$B:$B,0)} -> 0
A4: Rot | B4: {=_xlfn.XLOOKUP("Rot",Harmony_Inputs!$A:$A,Harmony_Inputs!$B:$B,0)} -> 0 | D4: Tier | E4: Calm/Steady/Wobbly/Frayed
A5: RequestsDone | B5: {=_xlfn.XLOOKUP("RequestsDone",Harmony_Inputs!$A:$A,Harmony_Inputs!$B:$B,0)} -> 0 | D5: =IF(E2>=80,"Calm",IF(E2>=60,"Steady",IF(E2>=40,"Wobbly","Frayed"))) -> 0 | E5: =IF(D5="Calm","Peace, for now.",IF(D5="Steady","We held together.",IF(D5="Wobbly","A near thing.","Barely holding on."))) -> 0
A6: RequestsIgnored | B6: {=_xlfn.XLOOKUP("RequestsIgnored",Harmony_Inputs!$A:$A,Harmony_Inputs!$B:$B,0)} -> 0
A7: AvgBond | B7: {=_xlfn.XLOOKUP("AvgBond",Harmony_Inputs!$A:$A,Harmony_Inputs!$B:$B,0)} -> 0 | D7: Estimated Grace Today | E7: =B9*(1+B10) -> 0
A8: NightCleansed | B8: {=_xlfn.XLOOKUP("NightCleansed",Harmony_Inputs!$A:$A,Harmony_Inputs!$B:$B,0)} -> 0
A9: RitualGrace | B9: {=_xlfn.XLOOKUP("RitualGrace",Harmony_Inputs!$A:$A,Harmony_Inputs!$B:$B,0)} -> 0
A10: (Change inputs in Harmony_Inputs to simulate days.) | B10: {=_xlfn.XLOOKUP("HarmonyBonus",Harmony_Inputs!$A:$A,Harmony_Inputs!$B:$B,0)} -> 0
A11: (Open Followers/Rituals workbooks to enable External_Data live links.)

Sheet Contributions
A1: Component | B1: Weight | C1: Computed
A2: Component | B2: Weight | C2: ='Harmony_Dashboard'!B2*50 -> 0
A3: Contentment | B3: 50 | C3: ='Harmony_Dashboard'!B5*2 -> 0
A4: RequestsDone | B4: 2 | C4: ='Harmony_Dashboard'!B8*2 -> 0
A5: NightCleansed | B5: 2 | C5: ='Harmony_Dashboard'!B3*(-3) -> 0
A6: Leaks | B6: -3 | C6: ='Harmony_Dashboard'!B4*(-5) -> 0
A7: Rot | B7: -5 | C7: ='Harmony_Dashboard'!B6*(-2) -> 0
A8: RequestsIgnored | B8: -2 | C8: ='Harmony_Dashboard'!B7*3 -> 0
A9: AvgBond | B9: 3
