Workbook

Sheet Overview
A1: Field | B1: Description
A2: System Name | B2: Rituals & Altar System
A3: Tagline | B3: Care, cleanse, bind, and let go — ceremonies that keep the afterlife from unraveling.
A4: Purpose | B4: Provide powerful, schedule-defining actions that stabilize mood, progress the world, and convert resources into Grace.
A5: One‑line Summary | B5: Perform rituals at the Altar to cleanse Manifest, feed many, bind new spirits, or release the ready — trading resources for harmony and growth.
A6: Core Loop | B6: Gather → Prepare → Perform (costs/cooldowns) → Resolve Effects → Generate Grace → Unlock Upgrades
A7: Key Systems Touched | B7: Contentment, Manifest/Ectoplasm, Appetite, Grace, Remains, Mementos, Temperaments, Garden, Charms, Requests
A8: Out of Scope (v1) | B8: Doctrine trees with large branches (keep it simple), multi-actor QTEs, long cutscenes.
A9: Success Criteria | B9: • Rituals feel meaningful and scarce • Costs/cooldowns pace the day • Grace flow is readable • Release moments are emotional and rewarded
A10: Author | B10: Brandon (Caretaker Designer)
A11: Version | B11: 1.0
A12: Last Updated | B12: 2025-11-01 02:38 UTC

Sheet Core_Loop
A1: Phase | B1: Name | C1: What Happens | D1: Rules | E1: UX Cues
A2: 1 | B2: Gather | C2: Collect Essence/Remains/Tokens; ensure spirits are calm enough to attend. | D2: Encourage care before ceremony; use Garden & Tasks to prep. | E2: HUD ritual-ready toasts; altar glow when possible.
A3: 2 | B3: Prepare | C3: Choose ritual, check costs & cooldown, select participants/targets. | D3: Some rituals stronger with happy participants (Fanatics, Storyteller boost). | E3: Ritual panel: costs, effects, cooldown timers, preview.
A4: 3 | B4: Perform | C4: Consume resources; play ceremony; apply effects globally/locally. | D4: Outcomes scale with Contentment; mishaps if mood is low. | E4: Short cinematic; VFX/SFX; UI ticker of results.
A5: 4 | B5: Resolve | C5: Spawn rewards (Grace, Memoria), adjust mood, clear Manifest/Rot, or bind/release spirits. | D5: Release is bittersweet: lose a worker, gain Memoria & Mementos. | E5: Result cards; dialogue barks; log entry.
A6: 5 | B6: Progress | C6: Spend Grace on upgrades; unlock new rituals or altar tiers. | D6: Pacing spine of mid-game; defines daily rhythm. | E6: Upgrade tree highlights; next goals surfaced.

Sheet Ritual_Types
A1: RitualID | B1: Display Name | C1: Primary Effect | D1: Theme
A2: CLEANSING | B2: Cleansing Wake | C2: Global cleanse of Manifest/Rot; +small Contentment pulse. | D2: Stability
A3: RELEASE | B3: Peaceful Release | C3: Let a ready spirit pass; yields Grace + Memoria + Mementos; removes worker. | D3: Closure
A4: BINDING | B4: Binding Ceremony | C4: Anchor a rescued spirit; adds worker; increases management challenge. | D4: Growth
A5: FEAST | B5: Feast of Remembrance | C5: Restore Appetite widely; +Contentment; small Grace if harmony high. | D5: Sustenance
A6: FESTIVAL | B6: Festival of Peace | C6: Area celebration; boosts aura plants; chance to trigger Peacebud. | D6: Harmony
A7: BANISH | B7: Mass Banish (risky) | C7: Forcefully remove 1–N ghosts; big cost; instant stability but morale hit. | D7: Emergency

Sheet Costs_Cooldowns
A1: RitualID | B1: Base Costs (Ess/Rem) | C1: Other Costs | D1: Cooldown | E1: Notes | F1: Total_Cost_Tokens | G1: Tokens_per_Grace (est)
A2: CLEANSING | B2: Essence:30, Remains:8 | C2: Tokens:0 | D2: 1 day | E2: Success ↑ if avg Contentment ≥ 60% | F2: 0 | G2: 0
A3: RELEASE | B3: Essence:10, Remains:2 | C3: Tokens:0 | D3: 3 days | E3: Yields Memoria:1, Grace:+5 (+bonus if Bond≥3) | F3: 0 | G3: 0
A4: BINDING | B4: Essence:15, Remains:0 | C4: Tokens:0 | D4: 2 days | E4: Adds Spirit; raises Decay Pressure slightly | F4: 0 | G4: 0
A5: FEAST | B5: Essence:20, Remains:0 | C5: Tokens:5 | D5: 2 days | E5: +Appetite to 100% in radius; +Contentment (+ more by Storyteller) | F5: 0 | G5: 0
A6: FESTIVAL | B6: Essence:40, Remains:4 | C6: Tokens:10, Medallions:1 | D6: 5 days | E6: Garden buff night; Peacebud chance if harmony high | F6: 0 | G6: 0
A7: BANISH | B7: Essence:5, Remains:6 | C7: Tokens:0 | D7: 4 days | E7: −Contentment global; stop-gap for chaos | F7: 0 | G7: 0

Sheet Interactions
A1: System | B1: Interaction
A2: Contentment | B2: Modifies success/mishap; many rituals affect mood directly.
A3: Manifest/Ectoplasm | B3: Cleansing removes leaks and Rot; reduces contagion for a time.
A4: Appetite | B4: Feast restores Appetite; pairs with Garden outputs and Offerings.
A5: Grace | B5: Primary source; spend on unlocks; gain is higher with harmony.
A6: Memoria | B6: From Release; permanent upgrades; shrine-building.
A7: Mementos | B7: Release gives Mementos; festivals can trickle extras.
A8: Temperaments | B8: Fanatics boost yields; Cold ignores morale buffs; others have custom reactions.
A9: Garden of Rest | B9: Festival amplifies auras; cleans Rot; boosts Ectofruit odds briefly.
A10: Charms | B10: Certain charms amplify/mitigate ritual effects or costs.
A11: Requests | B11: Some requests ask for a ritual (Release, Feast); fulfilling yields extra Bond/Grace.

Sheet Hooks
A1: Hook ID | B1: Context / Feature | C1: Unity Component / Script | D1: Key Fields / Serialized Props | E1: Events (Invoke/Listen) | F1: Triggered By | G1: Emits / Subscribes To | H1: Expected Prefab / Asset | I1: Notes / Integration
A2: HK_AltarController | B2: Central ritual manager | C2: KD.Rituals.AltarController | D2: unlocked[], cooldowns{}, queue[], modifiers{} | E2: OnRitualQueued, OnRitualStarted, OnRitualComplete | F2: Player UI; Grace unlocks; day state | G2: Emit: Ritual events; Sub: Mood/Time | H2: PF_Altar, UI_RitualPanel | I2: Persists cooldowns; drives VFX.
A3: HK_RitualPerformer | B3: Anim & sequencing | C3: KD.Rituals.RitualPerformer | D3: ritualId, participants[], vfxKeys[], sfxKeys[] | E3: OnRitualStarted, OnRitualStep | F3: AltarController | G3: Emit: Step events, mood pulses | H3: Anim_Ritual_[id], VFX_Ritual_[id] | I3: Keeps ceremony short & punchy.
A4: HK_RitualEffects | B4: Applies outcomes | C4: KD.Rituals.RitualEffects | D4: moodPulse, cleanseRadius, appetiteFill, graceYield | E4: OnRitualComplete | F4: RitualPerformer | G4: Emit: Rewards, ApplyBuffs | H4: — | I4: Contains balance table per ritual.
A5: HK_CooldownClock | B5: Cooldowns & timers | C5: KD.Rituals.CooldownClock | D5: cooldowns{}, lastPerformed{} | E5: OnDayStart/End | F5: TimeManager | G5: Emit: Cooldown UI updates | H5: UI_RitualCooldowns | I5: Sync with save/load.
A6: HK_GraceBank | B6: Grace accounting | C6: KD.Meta.GraceBank | D6: graceTotal, earnMult, spend() | E6: OnGraceEarned, OnGraceSpent | F6: RitualEffects | G6: Emit: Grace totals | H6: UI_GraceCounter | I6: Controls unlock pacing.

Sheet Tuning_Defaults
A1: Parameter | B1: Default | C1: Min | D1: Max | E1: Notes
A2: ritual_success_harmony_threshold | B2: 0.6 | C2: 0.4 | D2: 0.9 | E2: Avg Contentment above this → better yields; below → mishap chance
A3: ritual_mishap_base_chance | B3: 0.05 | C3: 0 | D3: 0.25 | E3: Base mishap chance if below threshold
A4: grace_per_release | B4: 5 | C4: 3 | D4: 10 | E4: Grace on Release (before bonuses)
A5: memoria_per_release | B5: 1 | C5: 1 | D5: 3 | E5: Memoria on Release
A6: feast_appetite_fill | B6: 1 | C6: 0.5 | D6: 1 | E6: Fraction of Appetite restored by Feast
A7: cleansing_radius | B7: 999 | C7: 6 | D7: 999 | E7: Global by default; can be local for variants
A8: festival_duration_min | B8: 3 | C8: 1 | D8: 5 | E8: Minutes of garden/celebration buff
A9: banish_contentment_penalty | B9: 3 | C9: 1 | D9: 10 | E9: Global −Contentment on Mass Banish

Sheet Resource_Summary
A1: Resource | B1: Description | C1: Acquired From | D1: Used For
A2: Essence | B2: Emotional energy to fuel ceremonies. | C2: Happy ghosts; dungeon drops. | D2: Primary ritual cost; upgrade conversions.
A3: Remains | B3: Ash/bone dust; the price of power. | C3: Dungeon runs; banishments; ritual aftermath. | D3: Catalyst for powerful or risky rituals.
A4: Tokens/Medallions | B4: Hard currency for lavish rites. | C4: Economy & exploration. | D4: Used in Feasts/Festivals; late-game costs.
A5: Grace | B5: The quiet permission of the dead. | C5: Ritual yields; releases; perfect care days. | D5: Meta-progression currency for unlocks.
A6: Memoria | B6: Prestige from letting go. | C6: Release ritual only. | D6: Permanent upgrades; shrines.

Sheet Visuals_FX
A1: Ritual | B1: VFX | C1: SFX
A2: Cleansing Wake | B2: Soft white wave clears leaks; candles brighten. | C2: Low bell; breathy choir pad.
A3: Peaceful Release | B3: Spirit drifts upward; petals fall; others bow. | C3: Sighs; light swell; single chime.
A4: Binding Ceremony | B4: Tether threads draw the rescued spirit in. | C4: Two-note motif; soft pulse.
A5: Feast of Remembrance | B5: Tables & bowls appear; warm light expands. | C5: Warm clinks; laughter murmur.
A6: Festival of Peace | B6: Lanterns, confetti bloom; garden glows. | C6: Festive loop; subtle crowd hum.
A7: Mass Banish | B7: Shadow snap; cold wind; candles snuff then relight. | C7: Bass hit; inhale; distant whisper.

Sheet Computed_Metrics
A1: Metric | B1: Formula (Excel) | C1: Var1 | D1: Var2 | E1: Var3 | F1: Var4 | G1: Notes
A2: Grace/Day (Release) | B2: 0 | C2: ReleasesPerDay | D2: grace_per_release | G2: Estimated Grace from Release per day
A3: Harmony Impact (Feast) | B3: 0 | C3: Targets | D3: feast_appetite_fill | E3: AppetiteToContentmentScalar | G3: Feast → Appetite → Contentment delta
A4: Mishap Risk (Cleansing) | B4: 0 | C4: AvgContentment | D4: ritual_success_harmony_threshold | E4: ritual_mishap_base_chance | G4: Chance a cleanse under low mood backfires
A5: Festival ROI | B5: 0 | C5: GraceFromFestival | D5: EssenceCost | E5: RemainsCost | F5: TokenCost | G5: Economy check vs benefits

Sheet External_Links
A1: LinkKey | B1: Excel_Formula | C1: Notes
A2: Essence_Token_Value | B2: 0 | C2: Live token value for 1 Essence (from Resources Globals)
A3: Remains_Token_Value | B3: 0 | C3: Live token value for 1 Remain (from Resources Globals)
A4: Token_Token_Value | B4: 0 | C4: Token face value (defaults to 1 if not present)
A5: Medallion_Token_Value | B5: 0 | C5: Medallion value (defaults to 25 if not present)

Sheet Efficiency_Inputs
A1: Key | B1: Value | C1: Notes
A2: Grace_Multiplier | B2: 1 | C2: Multiply Grace_Estimate to simulate harmony/participant bonuses (e.g., 1.15 = +15%)

Sheet Costs_Live
A1: RitualID | B1: Display Name | C1: Essence | D1: Remains | E1: Tokens | F1: Medallions | G1: Grace_Estimate | H1: Total_Cost_Tokens | I1: Grace_Adjusted | J1: Tokens_per_Grace (est)
A2: RitualID | B2: Display Name | C2: Essence | D2: Remains | E2: Tokens | F2: Medallions | G2: Grace_Estimate | H2: =C2*External_Links!B2 + D2*External_Links!B3 + E2*External_Links!B4 + F2*External_Links!B5 -> #VALUE! | I2: =G2*Efficiency_Inputs!B2 -> #VALUE! | J2: =IF(I2=0,"—",ROUND(H2/I2,2)) -> #VALUE!
A3: RitualID | B3: Display Name | C3: Essence | D3: Remains | E3: Tokens | F3: Medallions | G3: Grace_Estimate | H3: =C3*External_Links!B2 + D3*External_Links!B3 + E3*External_Links!B4 + F3*External_Links!B5 -> #VALUE! | I3: =G3*Efficiency_Inputs!B2 -> #VALUE! | J3: =IF(I3=0,"—",ROUND(H3/I3,2)) -> #VALUE!
A4: CLEANSING | B4: Cleansing Wake | C4: 30 | D4: 8 | E4: 0 | F4: 0 | G4: 0 | H4: =C4*External_Links!B2 + D4*External_Links!B3 + E4*External_Links!B4 + F4*External_Links!B5 -> 0 | I4: =G4*Efficiency_Inputs!B2 -> 0 | J4: =IF(I4=0,"—",ROUND(H4/I4,2)) -> —
A5: RELEASE | B5: Peaceful Release | C5: 10 | D5: 2 | E5: 0 | F5: 0 | G5: 5 | H5: =C5*External_Links!B2 + D5*External_Links!B3 + E5*External_Links!B4 + F5*External_Links!B5 -> 0 | I5: =G5*Efficiency_Inputs!B2 -> 5 | J5: =IF(I5=0,"—",ROUND(H5/I5,2)) -> 0
A6: BINDING | B6: Binding Ceremony | C6: 15 | D6: 0 | E6: 0 | F6: 0 | G6: 0 | H6: =C6*External_Links!B2 + D6*External_Links!B3 + E6*External_Links!B4 + F6*External_Links!B5 -> 0 | I6: =G6*Efficiency_Inputs!B2 -> 0 | J6: =IF(I6=0,"—",ROUND(H6/I6,2)) -> —
A7: FEAST | B7: Feast of Remembrance | C7: 20 | D7: 0 | E7: 5 | F7: 0 | G7: 2 | H7: =C7*External_Links!B2 + D7*External_Links!B3 + E7*External_Links!B4 + F7*External_Links!B5 -> 0 | I7: =G7*Efficiency_Inputs!B2 -> 2 | J7: =IF(I7=0,"—",ROUND(H7/I7,2)) -> 0
A8: FESTIVAL | B8: Festival of Peace | C8: 40 | D8: 4 | E8: 10 | F8: 1 | G8: 4 | H8: =C8*External_Links!B2 + D8*External_Links!B3 + E8*External_Links!B4 + F8*External_Links!B5 -> 0 | I8: =G8*Efficiency_Inputs!B2 -> 4 | J8: =IF(I8=0,"—",ROUND(H8/I8,2)) -> 0
A9: BANISH | B9: Mass Banish | C9: 5 | D9: 6 | E9: 0 | F9: 0 | G9: 0

Sheet Chart_Costs
A1: Display Name | B1: Total_Cost_Tokens | C1: Grace_Adjusted | D1: Tokens_per_Grace (est)
A2: Display Name | B2: {=_xlfn.XLOOKUP(A2,Costs_Live!$B:$B,Costs_Live!$H:$H,0)} -> Total_Cost_Tokens | C2: {=_xlfn.XLOOKUP(A2,Costs_Live!$B:$B,Costs_Live!$I:$I,0)} -> Grace_Adjusted | D2: {=_xlfn.XLOOKUP(A2,Costs_Live!$B:$B,Costs_Live!$J:$J,0)} -> Tokens_per_Grace (est)
A3: Cleansing Wake | B3: {=_xlfn.XLOOKUP(A3,Costs_Live!$B:$B,Costs_Live!$H:$H,0)} -> 0 | C3: {=_xlfn.XLOOKUP(A3,Costs_Live!$B:$B,Costs_Live!$I:$I,0)} -> 0 | D3: {=_xlfn.XLOOKUP(A3,Costs_Live!$B:$B,Costs_Live!$J:$J,0)} -> —
A4: Peaceful Release | B4: {=_xlfn.XLOOKUP(A4,Costs_Live!$B:$B,Costs_Live!$H:$H,0)} -> 0 | C4: {=_xlfn.XLOOKUP(A4,Costs_Live!$B:$B,Costs_Live!$I:$I,0)} -> 5 | D4: {=_xlfn.XLOOKUP(A4,Costs_Live!$B:$B,Costs_Live!$J:$J,0)} -> 0
A5: Binding Ceremony | B5: {=_xlfn.XLOOKUP(A5,Costs_Live!$B:$B,Costs_Live!$H:$H,0)} -> 0 | C5: {=_xlfn.XLOOKUP(A5,Costs_Live!$B:$B,Costs_Live!$I:$I,0)} -> 0 | D5: {=_xlfn.XLOOKUP(A5,Costs_Live!$B:$B,Costs_Live!$J:$J,0)} -> —
A6: Feast of Remembrance | B6: {=_xlfn.XLOOKUP(A6,Costs_Live!$B:$B,Costs_Live!$H:$H,0)} -> 0 | C6: {=_xlfn.XLOOKUP(A6,Costs_Live!$B:$B,Costs_Live!$I:$I,0)} -> 2 | D6: {=_xlfn.XLOOKUP(A6,Costs_Live!$B:$B,Costs_Live!$J:$J,0)} -> 0
A7: Festival of Peace | B7: {=_xlfn.XLOOKUP(A7,Costs_Live!$B:$B,Costs_Live!$H:$H,0)} -> 0 | C7: {=_xlfn.XLOOKUP(A7,Costs_Live!$B:$B,Costs_Live!$I:$I,0)} -> 4 | D7: {=_xlfn.XLOOKUP(A7,Costs_Live!$B:$B,Costs_Live!$J:$J,0)} -> 0
A8: Mass Banish | B8: {=_xlfn.XLOOKUP(A8,Costs_Live!$B:$B,Costs_Live!$H:$H,0)} -> 0 | C8: {=_xlfn.XLOOKUP(A8,Costs_Live!$B:$B,Costs_Live!$I:$I,0)} -> 0 | D8: {=_xlfn.XLOOKUP(A8,Costs_Live!$B:$B,Costs_Live!$J:$J,0)} -> 0
